base.py
generator.py
layers.py
oneplane.py
processor.py
sample.py
dlchess_rog-0.0.1.dist-info/METADATA
dlchess_rog-0.0.1.dist-info/WHEEL
dlchess_rog-0.0.1.dist-info/top_level.txt
dlchess_rog-0.0.1.dist-info/RECORD
