Metadata-Version: 2.1
Name: dlchess-rog
Version: 0.0.1
Summary: My chess bot modules
Home-page: UNKNOWN
Author: UNKNOWN
Author-email: UNKNOWN
License: UNKNOWN
Platform: UNKNOWN
